[
    {
        "id": "_meta",
        "name": "Reptiles! v1.4.1",
        "author": "Aero",
        "logo": "",
        "state": [
            {
                "stateName": "醉酒与中毒",
                "stateDescription": "中毒与醉酒的玩家失去技能，但他们仍然以为自己拥有技能，并且能够发动技能。中毒/醉酒期间发动的其他类型技能无效（一次性技能如果被触发则被消耗），信息类技能则大概率获取错误信息。"
            },
            {
                "stateName": "疯狂",
                "stateDescription": "当一名玩家对某事“疯狂”时，这就代表他们试图证明这件事是真的，例如：畸形秀演员对“我是外来者”疯狂，则代表他试图证明自己是外来者。"
            }
        ],
        "status": [
            {
                "name": "醉酒与中毒",
                "skill": "中毒与醉酒的玩家失去技能，但他们仍然以为自己拥有技能，并且能够发动技能。中毒/醉酒期间发动的其他类型技能无效（一次性技能如果被触发则被消耗），信息类技能则大概率获取错误信息。"
            },
            {
                "name": "疯狂",
                "skill": "当一名玩家对某事“疯狂”时，这就代表他们试图证明这件事是真的，例如：畸形秀演员对“我是外来者”疯狂，则代表他试图证明自己是外来者。"
            }
        ]
    },
    {
        "id": "ChefButton",
        "image": "https://oss.gstonegames.com/data_file/clocktower/web/icons/chef.png",
        "edition": "custom",
        "firstNight": 41,
        "firstNightReminder": "在首个夜晚里，唤醒厨师。为厨师用手势比划场上互为邻座的邪恶玩家有多少对（0，1，2，等等）。让厨师重新入睡。",
        "otherNight": 0,
        "otherNightReminder": "",
        "reminders": [
        ],
        "remindersGlobal": [
        ],
        "setup": false,
        "name": "厨师",
        "team": "townsfolk",
        "sch_team": "镇民",
        "ability": "在你的首个夜晚，你会得知场上邻座的邪恶玩家有多少对。"
    },
    {
        "id": "WasherwomanButton",
        "image": "https://oss.gstonegames.com/data_file/clocktower/web/icons/washerwoman.png",
        "edition": "custom",
        "firstNight": 38,
        "firstNightReminder": "在首个夜晚里，唤醒洗衣妇，并指向标记有“镇民”和“错误”的玩家。将标记有“镇民”的玩家标记展示给洗衣妇。让洗衣妇重新入睡。",
        "otherNight": 0,
        "otherNightReminder": "",
        "reminders": [
            "镇民",
            "错误"
        ],
        "remindersGlobal": [
        ],
        "setup": false,
        "name": "洗衣妇",
        "team": "townsfolk",
        "sch_team": "镇民",
        "ability": "在你的首个夜晚，你会得知两名玩家和一个镇民角色：这两名玩家之一是该角色。"
    },
    {
        "id": "LibrarianButton",
        "image": "https://oss.gstonegames.com/data_file/clocktower/web/icons/librarian.png",
        "edition": "custom",
        "firstNight": 39,
        "firstNightReminder": "在首个夜晚里，唤醒图书管理员，并指向标记有“外来者”和“错误”的玩家。将有“外来者”的玩家的角色标记展示给图书管理员。或者，如果说书人由于场上无外来者而未放置这两个标记，则对图书管理员展示手势“0”。让图书管理员重新入睡。",
        "otherNight": 0,
        "otherNightReminder": "",
        "reminders": [
            "外来者",
            "错误"
        ],
        "remindersGlobal": [
        ],
        "setup": false,
        "name": "图书管理员",
        "team": "townsfolk",
        "sch_team": "镇民",
        "ability": "在你的首个夜晚，你会得知两名玩家和一个外来者角色：这两名玩家之一是该角色（或者你会得知没有外来者在场）。"
    },
    {
        "id": "SailorButton",
        "image": "https://oss.gstonegames.com/data_file/clocktower/web/icons/sailor.png",
        "edition": "custom",
        "firstNight": 16,
        "firstNightReminder": "让水手选择一名存活玩家。标记那名玩家或水手醉酒。",
        "otherNight": 5,
        "otherNightReminder": "让水手选择一名存活玩家。标记那名玩家或水手醉酒。",
        "reminders": [
            "醉酒"
        ],
        "remindersGlobal": [
        ],
        "setup": false,
        "name": "水手",
        "team": "townsfolk",
        "sch_team": "镇民",
        "ability": "每个夜晚，你要选择一名存活的玩家：你或他之一会醉酒直到下个黄昏。你不会死亡。"
    },
    {
        "id": "GeneralButton",
        "image": "https://oss.gstonegames.com/data_file/clocktower/web/icons/general.png",
        "edition": "custom",
        "firstNight": 64,
        "firstNightReminder": "每个夜晚，唤醒将军。如果你认为善良阵营更具优势，给出拇指朝上的手势。如果你认为邪恶阵营更具优势，给出拇指朝下的手势。如果你不清楚哪一方更具优势，给出拇指水平指向一侧的手势。让将军重新入睡。",
        "otherNight": 85,
        "otherNightReminder": "每个夜晚，唤醒将军。如果你认为善良阵营更具优势，给出拇指朝上的手势。如果你认为邪恶阵营更具优势，给出拇指朝下的手势。如果你不清楚哪一方更具优势，给出拇指水平指向一侧的手势。让将军重新入睡。",
        "reminders": [
        ],
        "remindersGlobal": [
        ],
        "setup": false,
        "name": "将军",
        "team": "townsfolk",
        "sch_team": "镇民",
        "ability": "每个夜晚，你会得知说书人认为哪个阵营当前更有优势（善良/邪恶/均势）。"
    },
    {
        "id": "ChambermaidButton",
        "image": "https://oss.gstonegames.com/data_file/clocktower/web/icons/chambermaid.png",
        "edition": "custom",
        "firstNight": 65,
        "firstNightReminder": "每个夜晚，唤醒侍女。让侍女指向除自己外任意两名存活的玩家。用手势向侍女比划出所选角色中当晚被唤醒过的数量（0，1，或2）。让侍女重新入睡。如果没有两名存活玩家能够选择（由于主谋、僵怖等的能力造成），不要唤醒侍女。",
        "otherNight": 86,
        "otherNightReminder": "每个夜晚，唤醒侍女。让侍女指向除自己外任意两名存活的玩家。用手势向侍女比划出所选角色中当晚被唤醒过的数量（0，1，或2）。让侍女重新入睡。如果没有两名存活玩家能够选择（由于主谋、僵怖等的能力造成），不要唤醒侍女。",
        "reminders": [
        ],
        "remindersGlobal": [
        ],
        "setup": false,
        "name": "侍女",
        "team": "townsfolk",
        "sch_team": "镇民",
        "ability": "每个夜晚，你要选择除你以外的两名存活的玩家：你会得知他们中有几人在当晚因其自身能力而被唤醒。"
    },
    {
        "id": "Snake_CharmerButton",
        "image": "https://oss.gstonegames.com/data_file/clocktower/web/icons/snake_charmer.png",
        "edition": "custom",
        "firstNight": 24,
        "firstNightReminder": "让舞蛇人选择一名玩家。如果舞蛇人选中了恶魔：展示“你是”信息标记和恶魔角色标记。用拇指向下代表他阵营变为邪恶。在魔典中交换舞蛇人和恶魔的角色标记。让原来的舞蛇人重新入睡。唤醒原来的恶魔。对老恶魔展示“你是”信息标记和舞蛇人角色标记，并用拇指向上代表他阵营变为善良。",
        "otherNight": 12,
        "otherNightReminder": "让舞蛇人选择一名玩家。如果舞蛇人选中了恶魔：展示“你是”信息标记和恶魔角色标记。用拇指向下代表他阵营变为邪恶。在魔典中交换舞蛇人和恶魔的角色标记。让原来的舞蛇人重新入睡。唤醒原来的恶魔。对老恶魔展示“你是”信息标记和舞蛇人角色标记，并用拇指向上代表他阵营变为善良。",
        "reminders": [
            "中毒"
        ],
        "remindersGlobal": [
        ],
        "setup": false,
        "name": "舞蛇人",
        "team": "townsfolk",
        "sch_team": "镇民",
        "ability": "每个夜晚，你要选择一名存活的玩家：如果你选中了恶魔，你和他交换角色和阵营，然后他中毒。"
    },
    {
        "id": "FlowergirlButton",
        "image": "https://oss.gstonegames.com/data_file/clocktower/web/icons/flowergirl.png",
        "edition": "custom",
        "firstNight": 0,
        "firstNightReminder": "",
        "otherNight": 72,
        "otherNightReminder": "如果卖花女孩被标记为“恶魔未投票”，摇头告知否。如果卖花女孩被标记为“恶魔已投票”，点头告知是。让卖花女孩重新入睡。",
        "reminders": [
            "恶魔未投票",
            "恶魔已投票"
        ],
        "remindersGlobal": [
        ],
        "setup": false,
        "name": "卖花女孩",
        "team": "townsfolk",
        "sch_team": "镇民",
        "ability": "每个夜晚*，你会得知在今天白天时是否有恶魔投过票。"
    },
    {
        "id": "UndertakerButton",
        "image": "https://oss.gstonegames.com/data_file/clocktower/web/icons/undertaker.png",
        "edition": "custom",
        "firstNight": 0,
        "firstNightReminder": "",
        "otherNight": 70,
        "otherNightReminder": "如果当天有任何玩家死于处决，唤醒送葬者。向他展示被标记了“死于今日”的角色标记。让送葬者重新入睡。",
        "reminders": [
            "死于今日"
        ],
        "remindersGlobal": [
        ],
        "setup": false,
        "name": "送葬者",
        "team": "townsfolk",
        "sch_team": "镇民",
        "ability": "每个夜晚*，你会得知今天白天死于处决的玩家的角色。"
    },
    {
        "id": "InnkeeperButton",
        "image": "https://oss.gstonegames.com/data_file/clocktower/web/icons/innkeeper.png",
        "edition": "custom",
        "firstNight": 0,
        "firstNightReminder": "",
        "otherNight": 9,
        "otherNightReminder": "让旅店老板选择两名玩家。标记这两名玩家不会死亡，并标记其中一人醉酒。",
        "reminders": [
            "不会死亡",
            "醉酒"
        ],
        "remindersGlobal": [
        ],
        "setup": false,
        "name": "旅店老板",
        "team": "townsfolk",
        "sch_team": "镇民",
        "ability": "每个夜晚*，你要选择两名玩家：他们当晚不会死亡，但其中一人会醉酒到下个黄昏。"
    },
    {
        "id": "PhilosopherButton",
        "image": "https://oss.gstonegames.com/data_file/clocktower/web/icons/philosopher.png",
        "edition": "custom",
        "firstNight": 3,
        "firstNightReminder": "哲学家可以选择一个角色。如果选择的角色不在场，将哲学家的角色标记替换成对应角色，并标记“是哲学家”，否则标记该角色对应的玩家醉酒。从现在开始，你需要以哲学家获得能力的那种角色的行动方式来唤醒哲学家。",
        "otherNight": 3,
        "otherNightReminder": "哲学家可以选择一个角色。如果选择的角色不在场，将哲学家的角色标记替换成对应角色，并标记“是哲学家”，否则标记该角色对应的玩家醉酒。从现在开始，你需要以哲学家获得能力的那种角色的行动方式来唤醒哲学家。",
        "reminders": [
        ],
        "remindersGlobal": [
            "醉酒",
            "是哲学家"
        ],
        "setup": false,
        "name": "哲学家",
        "team": "townsfolk",
        "sch_team": "镇民",
        "ability": "每局游戏限一次，在夜晚时，你可以选择一个善良角色：你获得该角色的能力。如果这个角色在场，他醉酒。"
    },
    {
        "id": "FoolButton",
        "image": "https://oss.gstonegames.com/data_file/clocktower/web/icons/fool.png",
        "edition": "custom",
        "firstNight": 0,
        "firstNightReminder": "",
        "otherNight": 0,
        "otherNightReminder": "",
        "reminders": [
            "失去能力"
        ],
        "remindersGlobal": [
        ],
        "setup": false,
        "name": "弄臣",
        "team": "townsfolk",
        "sch_team": "镇民",
        "ability": "当你首次将要死亡时，你不会死亡。"
    },
    {
        "id": "Tea_LadyButton",
        "image": "https://oss.gstonegames.com/data_file/clocktower/web/icons/tea_lady.png",
        "edition": "custom",
        "firstNight": 0,
        "firstNightReminder": "",
        "otherNight": 0,
        "otherNightReminder": "",
        "reminders": [
            "不会死亡"
        ],
        "remindersGlobal": [
        ],
        "setup": false,
        "name": "茶艺师",
        "team": "townsfolk",
        "sch_team": "镇民",
        "ability": "如果与你邻近的两名存活的玩家是善良的，他们不会死亡。"
    },
    {
        "id": "VirginButton",
        "image": "https://oss.gstonegames.com/data_file/clocktower/web/icons/virgin.png",
        "edition": "custom",
        "firstNight": 0,
        "firstNightReminder": "",
        "otherNight": 0,
        "otherNightReminder": "",
        "reminders": [
            "失去能力"
        ],
        "remindersGlobal": [
        ],
        "setup": false,
        "name": "贞洁者",
        "team": "townsfolk",
        "sch_team": "镇民",
        "ability": "当你首次被提名时，如果提名你的玩家是镇民，他立刻被处决。"
    },
    {
        "id": "SaintButton",
        "image": "https://oss.gstonegames.com/data_file/clocktower/web/icons/saint.png",
        "edition": "custom",
        "firstNight": 0,
        "firstNightReminder": "",
        "otherNight": 0,
        "otherNightReminder": "",
        "reminders": [
        ],
        "remindersGlobal": [
        ],
        "setup": false,
        "name": "圣徒",
        "team": "outsider",
        "sch_team": "外来",
        "ability": "如果你死于处决，你的阵营落败。"
    },
    {
        "id": "SweetheartButton",
        "image": "https://oss.gstonegames.com/data_file/clocktower/web/icons/sweetheart.png",
        "edition": "custom",
        "firstNight": 0,
        "firstNightReminder": "",
        "otherNight": 59,
        "otherNightReminder": "如果心上人死亡，你选择任一玩家醉酒，为他放置“醉酒”提示标记。心上人在死亡时不会失去该能力。",
        "reminders": [
            "醉酒"
        ],
        "remindersGlobal": [
        ],
        "setup": false,
        "name": "心上人",
        "team": "outsider",
        "sch_team": "外来",
        "ability": "当你死亡时，会有一名玩家开始醉酒。"
    },
    {
        "id": "HereticButton",
        "image": "https://oss.gstonegames.com/data_file/clocktower/web/icons/heretic.png",
        "edition": "custom",
        "firstNight": 0,
        "firstNightReminder": "",
        "otherNight": 0,
        "otherNightReminder": "",
        "reminders": [
        ],
        "remindersGlobal": [
        ],
        "setup": false,
        "name": "异端分子",
        "team": "outsider",
        "sch_team": "外来",
        "ability": "对调胜负结果，即使你已死亡。"
    },
    {
        "id": "DrunkButton",
        "image": "https://oss.gstonegames.com/data_file/clocktower/web/icons/drunk.png",
        "edition": "custom",
        "firstNight": 0,
        "firstNightReminder": "",
        "otherNight": 0,
        "otherNightReminder": "",
        "reminders": [
        ],
        "remindersGlobal": [
            "是酒鬼"
        ],
        "setup": true,
        "name": "酒鬼",
        "team": "outsider",
        "sch_team": "外来",
        "ability": "你不知道你是酒鬼。你以为你是一个镇民角色，但其实你不是。"
    },
    {
        "id": "BarberButton",
        "image": "https://oss.gstonegames.com/data_file/clocktower/web/icons/barber.png",
        "edition": "custom",
        "firstNight": 0,
        "firstNightReminder": "",
        "otherNight": 40,
        "otherNightReminder": "如果理发师今天死亡了，唤醒恶魔并展示“该角色的效果对你生效”信息标记和理发师角色标记。如果恶魔选择了两名玩家，将这两名玩家分别独自唤醒。对他们展示“你是”信息标记和他们的新角色标记。",
        "reminders": [
            "今晚理发"
        ],
        "remindersGlobal": [
        ],
        "setup": false,
        "name": "理发师",
        "team": "outsider",
        "sch_team": "外来",
        "ability": "如果你死亡，在当晚恶魔可以选择两名玩家（不能选择其他恶魔）交换角色。"
    },
    {
        "id": "PoisonerButton",
        "image": "https://oss.gstonegames.com/data_file/clocktower/web/icons/poisoner.png",
        "edition": "custom",
        "firstNight": 21,
        "firstNightReminder": "让投毒者选择一名玩家。标记那名玩家中毒。",
        "otherNight": 8,
        "otherNightReminder": "让投毒者选择一名玩家。标记那名玩家中毒。",
        "reminders": [
            "中毒"
        ],
        "remindersGlobal": [
        ],
        "setup": false,
        "name": "投毒者",
        "team": "minion",
        "sch_team": "爪牙",
        "ability": "每个夜晚，你要选择一名玩家：他在当晚和明天白天中毒。"
    },
    {
        "id": "Devils_AdvocateButton",
        "image": "https://oss.gstonegames.com/data_file/clocktower/web/icons/devils_advocate.png",
        "edition": "custom",
        "firstNight": 22,
        "firstNightReminder": "让魔鬼代言人选择一名存活玩家。标记那名玩家处决不死。",
        "otherNight": 14,
        "otherNightReminder": "让魔鬼代言人选择一名存活玩家。标记那名玩家处决不死。",
        "reminders": [
        ],
        "remindersGlobal": [
            "处决不死"
        ],
        "setup": false,
        "name": "魔鬼代言人",
        "team": "minion",
        "sch_team": "爪牙",
        "ability": "每个夜晚，你要选择一名存活的玩家（与上个夜晚不同）：如果明天白天他被处决，他不会死亡。"
    },
    {
        "id": "SpyButton",
        "image": "https://oss.gstonegames.com/data_file/clocktower/web/icons/spy.png",
        "edition": "custom",
        "firstNight": 60,
        "firstNightReminder": "唤醒间谍并让他按自己意愿的时长来查看魔典。让间谍重新入睡。",
        "otherNight": 83,
        "otherNightReminder": "唤醒间谍并让他按自己意愿的时长来查看魔典。让间谍重新入睡。",
        "reminders": [
        ],
        "remindersGlobal": [
        ],
        "setup": false,
        "name": "间谍",
        "team": "minion",
        "sch_team": "爪牙",
        "ability": "每个夜晚，你能查看魔典。你可能会被当作善良阵营、镇民角色或外来者角色，即使你已死亡。"
    },
    {
        "id": "PsychopathButton",
        "image": "https://oss.gstonegames.com/data_file/clocktower/web/icons/psychopath.png",
        "edition": "custom",
        "firstNight": 0,
        "firstNightReminder": "",
        "otherNight": 0,
        "otherNightReminder": "",
        "reminders": [
        ],
        "remindersGlobal": [
        ],
        "setup": false,
        "name": "精神病患者",
        "team": "minion",
        "sch_team": "爪牙",
        "ability": "每个白天，在提名开始前，你可以公开选择一名玩家：他死亡。如果你被处决，提名你的玩家需要和你猜拳，只有你输了你才会死亡。"
    },
    {
        "id": "BaronButton",
        "image": "https://oss.gstonegames.com/data_file/clocktower/web/icons/baron.png",
        "edition": "custom",
        "firstNight": 0,
        "firstNightReminder": "",
        "otherNight": 0,
        "otherNightReminder": "",
        "reminders": [
        ],
        "remindersGlobal": [
        ],
        "setup": true,
        "name": "男爵",
        "team": "minion",
        "sch_team": "爪牙",
        "ability": "会有额外的外来者在场。[+2 外来者]"
    },
    {
        "id": "Al-HadikhiaButton",
        "image": "https://wiki.bloodontheclocktower.com/images/1/18/Icon_alhadikhia.png",
        "edition": "custom",
        "firstNight": 0,
        "firstNightReminder": "",
        "otherNight": 33,
        "otherNightReminder": "哈迪寂亚选择三名玩家。对所有人宣告第一名玩家，然后唤醒他并让他秘密选择活着还是死去。依次对第二、第三名玩家如此做。如果三名玩家都选择活着，他们都死去。",
        "reminders": [
            "选择生",
            "选择死"
        ],
        "remindersGlobal": [
            "1",
            "2",
            "3"
        ],
        "setup": false,
        "name": "哈迪寂亚",
        "team": "demon",
        "sch_team": "恶魔",
        "ability": "每个夜晚*，你要选择三名玩家（所有玩家都会得知你选了谁）：他们分别秘密决定自己的生死，然后如果他们都存活则都死亡。"
    },
    {
        "id": "PrimoButton",
        "image": "https://www.bloodstar.xyz//p//westwind//bb1//27_bb1.png",
        "edition": "custom",
        "firstNight": 0,
        "firstNightReminder": "",
        "otherNight": 0,
        "otherNightReminder": "",
        "reminders": [
        ],
        "remindersGlobal": [
        ],
        "setup": false,
        "name": "首席歌手",
        "team": "traveler",
        "sch_team": "旅行者",
        "ability": "在夜晚，你可以给大家唱首歌。如果你唱歌了，下一个白天你不能被流放，说书人可能会告诉你一条对你阵营有益的建议。"
    },
    {
        "id": "VendorButton",
        "image": "https://www.bloodstar.xyz/p/poi4399/7759/26_7759.png",
        "edition": "custom",
        "firstNight": 0,
        "firstNightReminder": "",
        "otherNight": 0,
        "otherNightReminder": "",
        "reminders": [
            "获得信息",
            "获得能力",
            "潘多拉的代价"
        ],
        "remindersGlobal": [
        ],
        "setup": false,
        "name": "古物商贩",
        "team": "traveler",
        "sch_team": "旅行者",
        "ability": "限一次，白天你可以打开魔盒获得一条重要信息或能力，但是会有人承担相对应的代价。"
    },
    {
        "id": "BeggarButton",
        "image": "https://oss.gstonegames.com/data_file/clocktower/web/icons/beggar.png",
        "edition": "custom",
        "firstNight": 0,
        "firstNightReminder": "",
        "otherNight": 0,
        "otherNightReminder": "",
        "reminders": [
        ],
        "remindersGlobal": [
        ],
        "setup": false,
        "name": "乞丐",
        "team": "traveler",
        "sch_team": "旅行者",
        "ability": "你只能使用投票标记才能投票。死亡的玩家可以将他的投票标记给你，如果他这么做，你会得知他的阵营。你不会中毒和醉酒。"
    },
    {
        "id": "MatronButton",
        "image": "https://oss.gstonegames.com/data_file/clocktower/web/icons/matron.png",
        "edition": "custom",
        "firstNight": 0,
        "firstNightReminder": "",
        "otherNight": 0,
        "otherNightReminder": "",
        "reminders": [
        ],
        "remindersGlobal": [
        ],
        "setup": false,
        "name": "女舍监",
        "team": "traveler",
        "sch_team": "旅行者",
        "ability": "每个白天，你可以选择至多三对玩家交换座位。玩家不能离开座位私聊。"
    },
    {
        "id": "VoudonButton",
        "image": "https://oss.gstonegames.com/data_file/clocktower/web/icons/voudon.png",
        "edition": "custom",
        "firstNight": 0,
        "firstNightReminder": "",
        "otherNight": 0,
        "otherNightReminder": "",
        "reminders": [
        ],
        "remindersGlobal": [
        ],
        "setup": false,
        "name": "巫毒师",
        "team": "traveler",
        "sch_team": "旅行者",
        "ability": "只有你和死亡的玩家可以投票，且投票不需要使用投票标记。忽略票数需要过半的要求。"
    },
    {
        "id": "ApprenticeButton",
        "image": "https://oss.gstonegames.com/data_file/clocktower/web/icons/apprentice.png",
        "edition": "custom",
        "firstNight": 1,
        "firstNightReminder": "向学徒展示“你是”信息标记，然后展示一个镇民或爪牙的角色标记。在魔典上，将学徒的角色标记替换为刚刚展示的角色标记，并放置“是学徒”提示标记。",
        "otherNight": 0,
        "otherNightReminder": "",
        "reminders": [
            "是学徒"
        ],
        "remindersGlobal": [
        ],
        "setup": false,
        "name": "学徒",
        "team": "traveler",
        "sch_team": "旅行者",
        "ability": "在你的首个夜晚，如果你是善良的，你会获得一个镇民角色的能力；如果你是邪恶的，你会获得一个爪牙角色的能力。"
    },
    {
        "id": "DeviantButton",
        "image": "https://oss.gstonegames.com/data_file/clocktower/web/icons/deviant.png",
        "edition": "custom",
        "firstNight": 0,
        "firstNightReminder": "",
        "otherNight": 0,
        "otherNightReminder": "",
        "reminders": [
        ],
        "remindersGlobal": [
        ],
        "setup": false,
        "name": "怪咖",
        "team": "traveler",
        "sch_team": "旅行者",
        "ability": "如果你表现得很有趣，当天你不能被流放。"
    },
    {
        "id": "Bone_CollectorButton",
        "image": "https://oss.gstonegames.com/data_file/clocktower/web/icons/bone_collector.png",
        "edition": "custom",
        "firstNight": 0,
        "firstNightReminder": "",
        "otherNight": 1,
        "otherNightReminder": "唤醒集骨者。集骨者要么摇头表示不使用能力，或者是指向任何一名已死亡的玩家。",
        "reminders": [
            "重获能力",
            "失去能力"
        ],
        "remindersGlobal": [
        ],
        "setup": false,
        "name": "集骨者",
        "team": "traveler",
        "sch_team": "旅行者",
        "ability": "每局游戏限一次，在夜晚时*，你可以选择一名死亡的玩家：他重新获得能力直到下个黄昏。"
    },
    {
        "id": "BaristaButton",
        "image": "https://oss.gstonegames.com/data_file/clocktower/web/icons/barista.png",
        "edition": "custom",
        "firstNight": 1,
        "firstNightReminder": "说书人选择一名玩家唤醒，并告诉他触发了咖啡师的什么效果。",
        "otherNight": 1,
        "otherNightReminder": "说书人选择一名玩家唤醒，并告诉他触发了咖啡师的什么效果。",
        "reminders": [
            "清醒且健康",
            "行动两次",
            "？"
        ],
        "remindersGlobal": [
        ],
        "setup": false,
        "name": "咖啡师",
        "team": "traveler",
        "sch_team": "旅行者",
        "ability": "每个夜晚，直至下个黄昏，由说书人二选一：1）一名玩家解除并免受醉酒和中毒影响，且会得知正确信息；2）一名玩家的能力可以生效两次。该玩家会得知是哪个效果。"
    },
    {
        "id": "HarlotButton",
        "image": "https://oss.gstonegames.com/data_file/clocktower/web/icons/harlot.png",
        "edition": "custom",
        "firstNight": 0,
        "firstNightReminder": "",
        "otherNight": 1,
        "otherNightReminder": "流莺选择一名玩家，将其唤醒，那名玩家选择同意或拒绝。如果同意，将他的角色标记展示给流莺看。然后说书人可以决定两名玩家是否会一起死去。",
        "reminders": [
            "死亡"
        ],
        "remindersGlobal": [
        ],
        "setup": false,
        "name": "流莺",
        "team": "traveler",
        "sch_team": "旅行者",
        "ability": "每个夜晚*，你要选择一名存活的玩家：如果他同意，你会得知他的角色，但是你们两个可能同时死亡。"
    },
    {
        "id": "GangsterButton",
        "image": "https://oss.gstonegames.com/data_file/clocktower/web/icons/gangster.png",
        "edition": "custom",
        "firstNight": 0,
        "firstNightReminder": "",
        "otherNight": 0,
        "otherNightReminder": "",
        "reminders": [
        ],
        "remindersGlobal": [
        ],
        "setup": false,
        "name": "黑帮",
        "team": "traveler",
        "sch_team": "旅行者",
        "ability": "每个白天限一次，你可以杀死与你邻近的两名存活的玩家中的一名，但需要另一边那个存活的玩家同意。"
    },
    {
        "id": "DoomsayerButton",
        "image": "https://oss.gstonegames.com/data_file/clocktower/web/icons/doomsayer.png",
        "edition": "custom",
        "firstNight": 0,
        "firstNightReminder": "",
        "otherNight": 0,
        "otherNightReminder": "",
        "reminders": [
        ],
        "remindersGlobal": [
        ],
        "setup": false,
        "name": "末日预言者",
        "team": "fabled",
        "sch_team": "传奇角色",
        "ability": "如果大于等于四名玩家存活，每名当前存活的玩家可以公开要求你杀死一名与他阵营相同的玩家（每名玩家限一次）。"
    },
    {
        "id": "AngelButton",
        "image": "https://oss.gstonegames.com/data_file/clocktower/web/icons/angel.png",
        "edition": "custom",
        "firstNight": 0,
        "firstNightReminder": "",
        "otherNight": 0,
        "otherNightReminder": "",
        "reminders": [
            "庇护",
            "不好的事"
        ],
        "remindersGlobal": [
        ],
        "setup": false,
        "name": "天使",
        "team": "fabled",
        "sch_team": "传奇角色",
        "ability": "对新玩家的死亡负最大责任的人，可能会遭遇一些不好的事情。"
    },
    {
        "id": "BuddhistButton",
        "image": "https://oss.gstonegames.com/data_file/clocktower/web/icons/buddhist.png",
        "edition": "custom",
        "firstNight": 0,
        "firstNightReminder": "",
        "otherNight": 0,
        "otherNightReminder": "",
        "reminders": [
        ],
        "remindersGlobal": [
        ],
        "setup": false,
        "name": "佛教徒",
        "team": "fabled",
        "sch_team": "传奇角色",
        "ability": "每个白天的前两分钟老玩家不能发言。"
    },
    {
        "id": "Hells_LibrarianButton",
        "image": "https://oss.gstonegames.com/data_file/clocktower/web/icons/hells_librarian.png",
        "edition": "custom",
        "firstNight": 0,
        "firstNightReminder": "",
        "otherNight": 0,
        "otherNightReminder": "",
        "reminders": [
            "不好的事"
        ],
        "remindersGlobal": [
        ],
        "setup": false,
        "name": "地狱藏书员",
        "team": "fabled",
        "sch_team": "传奇角色",
        "ability": "当说书人宣布安静时，仍在说话的玩家可能会遭遇一些不好的事情。"
    },
    {
        "id": "FiddlerButton",
        "image": "https://oss.gstonegames.com/data_file/clocktower/web/icons/fiddler.png",
        "edition": "custom",
        "firstNight": 0,
        "firstNightReminder": "",
        "otherNight": 0,
        "otherNightReminder": "",
        "reminders": [
        ],
        "remindersGlobal": [
        ],
        "setup": false,
        "name": "小提琴手",
        "team": "fabled",
        "sch_team": "传奇角色",
        "ability": "每局游戏限一次，恶魔可以秘密选择一名对立阵营的玩家，所有玩家要表决：这两名玩家中谁的阵营获胜。（平局邪恶阵营获胜）"
    },
    {
        "id": "DuchessButton",
        "image": "https://oss.gstonegames.com/data_file/clocktower/web/icons/duchess.png",
        "edition": "custom",
        "firstNight": 0,
        "firstNightReminder": "",
        "otherNight": 0,
        "otherNightReminder": "",
        "reminders": [
            "访客",
            "错误信息"
        ],
        "remindersGlobal": [
        ],
        "setup": false,
        "name": "公爵夫人",
        "team": "fabled",
        "sch_team": "传奇角色",
        "ability": "每个白天，三名玩家可以一起拜访你。当晚*，他们会得知他们之中有几个是邪恶的，但其中一人的信息是错的。"
    },
    {
        "id": "Spirit_Of_IvoryButton",
        "image": "https://oss.gstonegames.com/data_file/clocktower/web/icons/spirit_of_ivory.png",
        "edition": "custom",
        "firstNight": 0,
        "firstNightReminder": "",
        "otherNight": 0,
        "otherNightReminder": "",
        "reminders": [
            "禁止邪恶"
        ],
        "remindersGlobal": [
        ],
        "setup": false,
        "name": "圣洁之魂",
        "team": "fabled",
        "sch_team": "传奇角色",
        "ability": "游戏过程中邪恶玩家的总数最多能比初始设置多一名。"
    },
    {
        "id": "DjinnButton",
        "image": "https://oss.gstonegames.com/data_file/clocktower/web/icons/djinn.png",
        "edition": "custom",
        "firstNight": 0,
        "firstNightReminder": "",
        "otherNight": 0,
        "otherNightReminder": "",
        "reminders": [
        ],
        "remindersGlobal": [
        ],
        "setup": false,
        "name": "灯神",
        "team": "fabled",
        "sch_team": "传奇角色",
        "ability": "使用灯神的相克规则。所有玩家都会知道其内容。"
    },
    {
        "id": "BootleggerButton",
        "image": "https://oss.gstonegames.com/data_file/clocktower/web/icons/bootlegger.png",
        "edition": "custom",
        "firstNight": 0,
        "firstNightReminder": "",
        "otherNight": 0,
        "otherNightReminder": "",
        "reminders": [
        ],
        "remindersGlobal": [
        ],
        "setup": false,
        "name": "私货商人",
        "team": "fabled",
        "sch_team": "传奇角色",
        "ability": "这个剧本包含有自制角色或自制规则。"
    },
    {
        "id": "FerrymanButton",
        "image": "https://wiki.bloodontheclocktower.com/images/8/8f/Icon_ferryman.png",
        "edition": "custom",
        "firstNight": 0,
        "firstNightReminder": "",
        "otherNight": 0,
        "otherNightReminder": "",
        "reminders": [
        ],
        "remindersGlobal": [
        ],
        "setup": false,
        "name": "摆渡人",
        "team": "fabled",
        "sch_team": "传奇角色",
        "ability": "在游戏的最后一天，所有已死亡玩家会重新获得投票标记。"
    },
    {
        "id": "GardenerButton",
        "image": "https://oss.gstonegames.com/data_file/clocktower/web/icons/gardener.png",
        "edition": "custom",
        "firstNight": 0,
        "firstNightReminder": "",
        "otherNight": 0,
        "otherNightReminder": "",
        "reminders": [
        ],
        "remindersGlobal": [
        ],
        "setup": false,
        "name": "园丁",
        "team": "fabled",
        "sch_team": "传奇角色",
        "ability": "由说书人来为一名或更多玩家派发角色。"
    },
    {
        "id": "Storm_CatcherButton",
        "image": "https://oss.gstonegames.com/data_file/clocktower/web/icons/stormcatcher.png",
        "edition": "custom",
        "firstNight": 1,
        "firstNightReminder": "标记一个善良玩家安全，或者不标。依次唤醒所有邪恶玩家并告知谁是安全的，或者不唤醒。",
        "otherNight": 0,
        "otherNightReminder": "",
        "reminders": [
        ],
        "remindersGlobal": [
        ],
        "setup": false,
        "name": "暴风捕手",
        "team": "fabled",
        "sch_team": "传奇角色",
        "ability": "游戏开始时，你要宣布一个善良角色。如果该角色在场，他只能死于处决，但所有邪恶玩家会在首个夜晚得知他是哪一名玩家。"
    }
]