[
    {
        "id": "_meta",
        "name": "Trust No One v1.0.0",
        "author": "",
        "logo": "",
        "state": [
            {
                "stateName": "醉酒与中毒",
                "stateDescription": "中毒与醉酒的玩家失去技能，但他们仍然以为自己拥有技能，并且能够发动技能。中毒/醉酒期间发动的其他类型技能无效（一次性技能如果被触发则被消耗），信息类技能则大概率获取错误信息。"
            },
            {
                "stateName": "疯狂",
                "stateDescription": "当一名玩家对某事“疯狂”时，这就代表他们试图证明这件事是真的，例如：畸形秀演员对“我是外来者”疯狂，则代表他试图证明自己是外来者。"
            }
        ],
        "status": [
            {
                "name": "醉酒与中毒",
                "skill": "中毒与醉酒的玩家失去技能，但他们仍然以为自己拥有技能，并且能够发动技能。中毒/醉酒期间发动的其他类型技能无效（一次性技能如果被触发则被消耗），信息类技能则大概率获取错误信息。"
            },
            {
                "name": "疯狂",
                "skill": "当一名玩家对某事“疯狂”时，这就代表他们试图证明这件事是真的，例如：畸形秀演员对“我是外来者”疯狂，则代表他试图证明自己是外来者。"
            }
        ]
    },
    {
        "id": "Noble_Button",
        "image": "https://oss.gstonegames.com/data_file/clocktower/web/icons/noble.png",
        "edition": "custom",
        "firstNight": 53,
        "firstNightReminder": "在首个夜晚，唤醒贵族，并指向三名标记有“得知”的玩家。让贵族重新入睡。",
        "otherNight": 0,
        "otherNightReminder": "",
        "reminders": [
            "被得知"
        ],
        "remindersGlobal": [
        ],
        "setup": false,
        "name": "贵族",
        "team": "townsfolk",
        "sch_team": "镇民",
        "ability": "在你的首个夜晚，你会得知三名玩家：其中有且只有一名玩家是邪恶的。"
    },
    {
        "id": "Clockmaker_Button",
        "image": "https://oss.gstonegames.com/data_file/clocktower/web/icons/clockmaker.png",
        "edition": "custom",
        "firstNight": 47,
        "firstNightReminder": "给他展示数字手势来告诉他恶魔与爪牙之间最近的距离",
        "otherNight": 0,
        "otherNightReminder": "",
        "reminders": [
        ],
        "remindersGlobal": [
        ],
        "setup": false,
        "name": "钟表匠",
        "team": "townsfolk",
        "sch_team": "镇民",
        "ability": "在你的首个夜晚，你会得知恶魔与爪牙之间最近的距离。（邻座的玩家距离为1）"
    },
    {
        "id": "Pixie_Button",
        "image": "https://oss.gstonegames.com/data_file/clocktower/web/icons/pixie.png",
        "edition": "custom",
        "firstNight": 36,
        "firstNightReminder": "对小精灵展示一个在场的镇民角色。",
        "otherNight": 0,
        "otherNightReminder": "",
        "reminders": [
            "疯狂",
            "获得能力"
        ],
        "remindersGlobal": [
        ],
        "setup": false,
        "name": "小精灵",
        "team": "townsfolk",
        "sch_team": "镇民",
        "ability": "在你的首个夜晚，你会得知一个在场的镇民角色。如果你“疯狂”地证明你是该角色，当他死亡时你获得该角色的能力。"
    },
    {
        "id": "Balloonist_Button",
        "image": "https://oss.gstonegames.com/data_file/clocktower/web/icons/balloonist.png",
        "edition": "custom",
        "firstNight": 53,
        "firstNightReminder": "选择一种角色类型，并告知其一个符合该类型的玩家。在该玩家旁边标记已被知晓。",
        "otherNight": 78,
        "otherNightReminder": "选择一种尚未被气球驾驶员知晓的角色类型，并告知其一个符合该类型的玩家。在该玩家旁边标记已被知晓。如果所有类型均已被知晓或无该种类型，气球驾驶员不会醒来。",
        "reminders": [
            "得知镇民",
            "得知外来者",
            "得知爪牙",
            "得知恶魔",
            "得知旅行者"
        ],
        "remindersGlobal": [
        ],
        "setup": true,
        "name": "气球驾驶员",
        "team": "townsfolk",
        "sch_team": "镇民",
        "ability": "每个夜晚，你会得知一名不同角色类型的玩家，直到场上所有的角色类型你都得知过一次。[+1 外来者]"
    },
    {
        "id": "Fortune_Teller_Button",
        "image": "https://oss.gstonegames.com/data_file/clocktower/web/icons/fortune_teller.png",
        "edition": "custom",
        "firstNight": 43,
        "firstNightReminder": "让占卜师选择两名玩家。如果其中有恶魔或“干扰项”，点头示意，否则摇头。",
        "otherNight": 69,
        "otherNightReminder": "让占卜师选择两名玩家。如果其中有恶魔或“干扰项”，点头示意，否则摇头。",
        "reminders": [
            "干扰项"
        ],
        "remindersGlobal": [
        ],
        "setup": false,
        "name": "占卜师",
        "team": "townsfolk",
        "sch_team": "镇民",
        "ability": "每个夜晚，你要选择两名玩家：你会得知他们之中是否有恶魔。会有一名善良玩家始终被你的能力当作恶魔。"
    },
    {
        "id": "Snake_Charmer_Button",
        "image": "https://oss.gstonegames.com/data_file/clocktower/web/icons/snake_charmer.png",
        "edition": "custom",
        "firstNight": 24,
        "firstNightReminder": "让舞蛇人选择一名玩家。如果舞蛇人选中了恶魔：展示“你是”信息标记和恶魔角色标记。用拇指向下代表他阵营变为邪恶。在魔典中交换舞蛇人和恶魔的角色标记。让原来的舞蛇人重新入睡。唤醒原来的恶魔。对老恶魔展示“你是”信息标记和舞蛇人角色标记，并用拇指向上代表他阵营变为善良。",
        "otherNight": 12,
        "otherNightReminder": "让舞蛇人选择一名玩家。如果舞蛇人选中了恶魔：展示“你是”信息标记和恶魔角色标记。用拇指向下代表他阵营变为邪恶。在魔典中交换舞蛇人和恶魔的角色标记。让原来的舞蛇人重新入睡。唤醒原来的恶魔。对老恶魔展示“你是”信息标记和舞蛇人角色标记，并用拇指向上代表他阵营变为善良。",
        "reminders": [
            "中毒"
        ],
        "remindersGlobal": [
        ],
        "setup": false,
        "name": "舞蛇人",
        "team": "townsfolk",
        "sch_team": "镇民",
        "ability": "每个夜晚，你要选择一名存活的玩家：如果你选中了恶魔，你和他交换角色和阵营，然后他中毒。"
    },
    {
        "id": "SavantButton",
        "image": "https://oss.gstonegames.com/data_file/clocktower/web/icons/savant.png",
        "edition": "custom",
        "firstNight": 0,
        "firstNightReminder": "",
        "otherNight": 0,
        "otherNightReminder": "",
        "reminders": [
        ],
        "remindersGlobal": [
        ],
        "setup": false,
        "name": "博学者",
        "team": "townsfolk",
        "sch_team": "镇民",
        "ability": "每个白天，你可以私下询问说书人以得知两条信息：一个是正确的，一个是错误的。"
    },
    {
        "id": "Amnesiac_Button",
        "image": "https://oss.gstonegames.com/data_file/clocktower/web/icons/amnesiac.png",
        "edition": "custom",
        "firstNight": 2,
        "firstNightReminder": "决定失忆者的能力。如果失忆者的能力会让他在今晚醒来：唤醒他并执行其能力。",
        "otherNight": 2,
        "otherNightReminder": "如果失忆者的能力会让他在今晚醒来：唤醒他并执行其能力。",
        "reminders": [
            "？"
        ],
        "remindersGlobal": [
        ],
        "setup": false,
        "name": "失忆者",
        "team": "townsfolk",
        "sch_team": "镇民",
        "ability": "你不知道你的能力是什么。每个白天你可以找说书人猜测一次，你会得知你的猜测有多准确。"
    },
    {
        "id": "Nightwatchman_Button",
        "image": "https://oss.gstonegames.com/data_file/clocktower/web/icons/nightwatchman.png",
        "edition": "custom",
        "firstNight": 58,
        "firstNightReminder": "唤醒守夜人。如果他摇头不使用能力，让他重新入睡。如果他指向了一名玩家，让他重新入睡，并唤醒被他选择的玩家，对其展示“该角色的能力对你生效”提示标记，守夜人的角色标记，然后指向守夜人玩家，随后让该玩家重新入睡。使用守夜人的“失去能力”标记标记守夜人。守夜人的能力被使用，将守夜人的夜晚标记从夜晚顺序表旁移除，在此后的夜晚中，不要再唤醒守夜人。",
        "otherNight": 82,
        "otherNightReminder": "唤醒守夜人。如果他摇头不使用能力，让他重新入睡。如果他指向了一名玩家，让他重新入睡，并唤醒被他选择的玩家，对其展示“该角色的能力对你生效”提示标记，守夜人的角色标记，然后指向守夜人玩家，随后让该玩家重新入睡。使用守夜人的“失去能力”标记标记守夜人。守夜人的能力被使用，将守夜人的夜晚标记从夜晚顺序表旁移除，在此后的夜晚中，不要再唤醒守夜人。",
        "reminders": [
            "失去能力"
        ],
        "remindersGlobal": [
        ],
        "setup": false,
        "name": "守夜人",
        "team": "townsfolk",
        "sch_team": "镇民",
        "ability": "每局游戏限一次，在夜晚时，你可以选择一名玩家：他会得知你是守夜人。"
    },
    {
        "id": "ArtistButton",
        "image": "https://oss.gstonegames.com/data_file/clocktower/web/icons/artist.png",
        "edition": "custom",
        "firstNight": 0,
        "firstNightReminder": "",
        "otherNight": 0,
        "otherNightReminder": "",
        "reminders": [
        ],
        "remindersGlobal": [
            "失去能力"
        ],
        "setup": false,
        "name": "艺术家",
        "team": "townsfolk",
        "sch_team": "镇民",
        "ability": "每局游戏限一次，在白天时，你可以私下询问说书人一个是非问题，你会得知该问题的答案。"
    },
    {
        "id": "Farmer_Button",
        "image": "https://oss.gstonegames.com/data_file/clocktower/web/icons/farmer.png",
        "edition": "custom",
        "firstNight": 0,
        "firstNightReminder": "",
        "otherNight": 65,
        "otherNightReminder": "如果农夫在夜晚死去，则选择另一名善良玩家成为农夫。唤醒这名玩家，并告知他成为了农夫。",
        "reminders": [
        ],
        "remindersGlobal": [
        ],
        "setup": false,
        "name": "农夫",
        "team": "townsfolk",
        "sch_team": "镇民",
        "ability": "如果你在夜晚死亡，一名存活的善良玩家会变成农夫。"
    },
    {
        "id": "MayorButton",
        "image": "https://oss.gstonegames.com/data_file/clocktower/web/icons/mayor.png",
        "edition": "custom",
        "firstNight": 0,
        "firstNightReminder": "",
        "otherNight": 0,
        "otherNightReminder": "",
        "reminders": [
        ],
        "remindersGlobal": [
        ],
        "setup": false,
        "name": "镇长",
        "team": "townsfolk",
        "sch_team": "镇民",
        "ability": "如果只有三名玩家存活且白天没有人被处决，你的阵营获胜。如果你在夜晚即将死亡，可能会有一名其他玩家代替你死亡。"
    },
    {
        "id": "CannibalButton",
        "image": "https://oss.gstonegames.com/data_file/clocktower/web/icons/cannibal.png",
        "edition": "custom",
        "firstNight": 0,
        "firstNightReminder": "",
        "otherNight": 0,
        "otherNightReminder": "",
        "reminders": [
            "死于今日",
            "中毒"
        ],
        "remindersGlobal": [
        ],
        "setup": false,
        "name": "食人族",
        "team": "townsfolk",
        "sch_team": "镇民",
        "ability": "你拥有上个死于处决的玩家的能力。如果该玩家属于邪恶阵营，你中毒直到下个善良玩家死于处决。"
    },
    {
        "id": "PuzzlemasterButton",
        "image": "https://oss.gstonegames.com/data_file/clocktower/web/icons/puzzlemaster.png",
        "edition": "custom",
        "firstNight": 0,
        "firstNightReminder": "",
        "otherNight": 0,
        "otherNightReminder": "",
        "reminders": [
            "醉酒",
            "已猜测"
        ],
        "remindersGlobal": [
        ],
        "setup": false,
        "name": "解谜大师",
        "team": "outsider",
        "sch_team": "外来",
        "ability": "一名玩家醉酒，即使你已死亡。每局游戏限一次，你可以猜测谁是那个醉酒的玩家，如果猜对了，你会得知谁是恶魔，但如果猜错了，你会得知错误的“谁是恶魔”信息。"
    },
    {
        "id": "RecluseButton",
        "image": "https://oss.gstonegames.com/data_file/clocktower/web/icons/recluse.png",
        "edition": "custom",
        "firstNight": 0,
        "firstNightReminder": "",
        "otherNight": 0,
        "otherNightReminder": "",
        "reminders": [
        ],
        "remindersGlobal": [
        ],
        "setup": false,
        "name": "陌客",
        "team": "outsider",
        "sch_team": "外来",
        "ability": "你可能会被当作邪恶阵营、爪牙角色或恶魔角色，即使你已死亡。"
    },
    {
        "id": "Lunatic_Button",
        "image": "https://oss.gstonegames.com/data_file/clocktower/web/icons/lunatic.png",
        "edition": "custom",
        "firstNight": 10,
        "firstNightReminder": "如果有七名或更多玩家，唤醒疯子：展示“他们是你的爪牙”信息标记。指向任意对应数量的玩家。展示“这些角色不在场”信息标记。展示三个善良角色。让疯子重新入睡。唤醒恶魔。展示“你是”信息标记和恶魔角色标记。展示“这名玩家是”信息标记和疯子角色标记，然后指向疯子玩家。",
        "otherNight": 27,
        "otherNightReminder": "做任何需要做的事情来模拟一位恶魔的行动。让疯子重新入睡。唤醒恶魔。对恶魔展示疯子角色标记，并指向疯子玩家，随后是疯子的攻击目标。",
        "reminders": [
            "被选择"
        ],
        "remindersGlobal": [
            "是疯子"
        ],
        "setup": true,
        "name": "疯子",
        "team": "outsider",
        "sch_team": "外来",
        "ability": "你以为你是一个恶魔，但其实你不是。恶魔知道你是疯子以及你在每个夜晚选择了哪些玩家。"
    },
    {
        "id": "MutantButton",
        "image": "https://oss.gstonegames.com/data_file/clocktower/web/icons/mutant.png",
        "edition": "custom",
        "firstNight": 0,
        "firstNightReminder": "",
        "otherNight": 0,
        "otherNightReminder": "",
        "reminders": [
        ],
        "remindersGlobal": [
        ],
        "setup": false,
        "name": "畸形秀演员",
        "team": "outsider",
        "sch_team": "外来",
        "ability": "如果你“疯狂”地证明自己是外来者，你可能被处决。"
    },
    {
        "id": "Widow_Button",
        "image": "https://oss.gstonegames.com/data_file/clocktower/web/icons/widow.png",
        "edition": "custom",
        "firstNight": 22,
        "firstNightReminder": "给寡妇展示魔典，她想看多久就看多久。等她看完后，让她指向一个玩家。那个玩家周公度。唤醒一名善良玩家，告诉他场上有寡妇。",
        "otherNight": 0,
        "otherNightReminder": "",
        "reminders": [
            "中毒"
        ],
        "remindersGlobal": [
            "被得知"
        ],
        "setup": false,
        "name": "寡妇",
        "team": "minion",
        "sch_team": "爪牙",
        "ability": "在你的首个夜晚，你能查看魔典并选择一名玩家：他中毒。随后，始终会有一名善良玩家知道寡妇在场。"
    },
    {
        "id": "Poisoner_Button",
        "image": "https://oss.gstonegames.com/data_file/clocktower/web/icons/poisoner.png",
        "edition": "custom",
        "firstNight": 21,
        "firstNightReminder": "让投毒者选择一名玩家。标记那名玩家中毒。",
        "otherNight": 8,
        "otherNightReminder": "让投毒者选择一名玩家。标记那名玩家中毒。",
        "reminders": [
            "中毒"
        ],
        "remindersGlobal": [
        ],
        "setup": false,
        "name": "投毒者",
        "team": "minion",
        "sch_team": "爪牙",
        "ability": "每个夜晚，你要选择一名玩家：他在当晚和明天白天中毒。"
    },
    {
        "id": "Cerenovus_Button",
        "image": "https://oss.gstonegames.com/data_file/clocktower/web/icons/cerenovus.png",
        "edition": "custom",
        "firstNight": 29,
        "firstNightReminder": "让洗脑师选择一名玩家和一个善良角色。标记那名玩家疯狂。让洗脑师重新入睡。唤醒洗脑师的目标。对这名玩家展示“该角色的能力对你生效”信息标记，洗脑师角色标记，该玩家需要疯狂证明的角色标记。",
        "otherNight": 19,
        "otherNightReminder": "让洗脑师选择一名玩家和一个善良角色。标记那名玩家疯狂。让洗脑师重新入睡。唤醒洗脑师的目标。对这名玩家展示“该角色的能力对你生效”信息标记，洗脑师角色标记，该玩家需要疯狂证明的角色标记。",
        "reminders": [
        ],
        "remindersGlobal": [
            "疯狂"
        ],
        "setup": false,
        "name": "洗脑师",
        "team": "minion",
        "sch_team": "爪牙",
        "ability": "每个夜晚，你要选择一名玩家和一个善良角色。他明天白天和夜晚需要“疯狂”地证明自己是这个角色，不然他可能被处决。"
    },
    {
        "id": "Marionette_Button",
        "image": "https://oss.gstonegames.com/data_file/clocktower/web/icons/marionette.png",
        "edition": "custom",
        "firstNight": 13,
        "firstNightReminder": "选择一个邻近恶魔的善良玩家放置提线木偶标记。唤醒恶魔并告知他谁是提线木偶。",
        "otherNight": 0,
        "otherNightReminder": "",
        "reminders": [
        ],
        "remindersGlobal": [
            "是提线木偶"
        ],
        "setup": true,
        "name": "提线木偶",
        "team": "minion",
        "sch_team": "爪牙",
        "ability": "你以为你是一个善良角色，但其实你不是。恶魔会知道你是提线木偶。[提线木偶会与恶魔邻座]"
    },
    {
        "id": "Imp_Button",
        "image": "https://oss.gstonegames.com/data_file/clocktower/web/icons/imp.png",
        "edition": "custom",
        "firstNight": 0,
        "firstNightReminder": "",
        "otherNight": 30,
        "otherNightReminder": "让小恶魔选择一名玩家。标记那名玩家死亡。如果小恶魔选择了自己：用一个备用的小恶魔标记替换一个存活的爪牙角色标记。让原来的小恶魔重新入睡。唤醒新的小恶魔。对他展示“你是”信息标记，和小恶魔角色标记。",
        "reminders": [
            "死亡"
        ],
        "remindersGlobal": [
        ],
        "setup": false,
        "name": "小恶魔",
        "team": "demon",
        "sch_team": "恶魔",
        "ability": "每个夜晚*，你要选择一名玩家：他死亡。如果你以这种方式自杀，一名爪牙会变成小恶魔。"
    },
    {
        "id": "Vigormortis_Button",
        "image": "https://oss.gstonegames.com/data_file/clocktower/web/icons/vigormortis.png",
        "edition": "custom",
        "firstNight": 0,
        "firstNightReminder": "",
        "otherNight": 39,
        "otherNightReminder": "让亡骨魔选择一名玩家。标记哪名玩家死亡。如果该玩家是爪牙，标记该玩家保留能力，并标记与该玩家邻近的镇民玩家之一中毒。",
        "reminders": [
            "死亡",
            "保留能力",
            "中毒"
        ],
        "remindersGlobal": [
        ],
        "setup": true,
        "name": "亡骨魔",
        "team": "demon",
        "sch_team": "恶魔",
        "ability": "每个夜晚*，你要选择一名玩家：他死亡。被你杀死的爪牙保留他的能力，且与他邻近的两名镇民之一中毒。[-1外来者]"
    },
    {
        "id": "Fang_Gu_Button",
        "image": "https://oss.gstonegames.com/data_file/clocktower/web/icons/fang_gu.png",
        "edition": "custom",
        "firstNight": 0,
        "firstNightReminder": "",
        "otherNight": 35,
        "otherNightReminder": "让方古选择一名玩家。标记那名玩家死亡。如果他选择了外来者，且“首次”标记未放置在魔典中：用备用的方古角色标记替换那名外来者的角色标记。让方古重新入睡。唤醒方古的目标玩家。对该玩家展示“你是”信息标记和方古角色标记，并用拇指向下代表他阵营变为邪恶。将“首次”标记放置在魔典中。标记原本的方古玩家死亡，且他选择的玩家不会被标记为死亡。",
        "reminders": [
            "死亡",
            "限一次"
        ],
        "remindersGlobal": [
        ],
        "setup": true,
        "name": "方古",
        "team": "demon",
        "sch_team": "恶魔",
        "ability": "每个夜晚*，你要选择一名玩家：他死亡。被该能力杀死的外来者改为变成邪恶的方古且你代替他死亡，但每局游戏仅能成功转化一次。[+1外来者]"
    },
    {
        "id": "Legion_Button",
        "image": "https://oss.gstonegames.com/data_file/clocktower/web/icons/legion.png",
        "edition": "custom",
        "firstNight": 0,
        "firstNightReminder": "",
        "otherNight": 38,
        "otherNightReminder": "由说书人决定，让哪一名玩家死亡。",
        "reminders": [
            "即将被处决"
        ],
        "remindersGlobal": [
        ],
        "setup": true,
        "name": "军团",
        "team": "demon",
        "sch_team": "恶魔",
        "ability": "每个夜晚*，可能有一名玩家死亡。如果一项提名只有邪恶玩家投票，投票无效。你也会被当作是爪牙。[半数以上玩家为军团]"
    },
    {
        "id": "PrimoButton",
        "image": "https://www.bloodstar.xyz//p//westwind//bb1//27_bb1.png",
        "edition": "custom",
        "firstNight": 0,
        "firstNightReminder": "",
        "otherNight": 0,
        "otherNightReminder": "",
        "reminders": [
        ],
        "remindersGlobal": [
        ],
        "setup": false,
        "name": "首席歌手",
        "team": "traveler",
        "sch_team": "旅行者",
        "ability": "在夜晚，你可以给大家唱首歌。如果你唱歌了，下一个白天你不能被流放，说书人可能会告诉你一条对你阵营有益的建议。"
    },
    {
        "id": "VendorButton",
        "image": "https://www.bloodstar.xyz/p/poi4399/7759/26_7759.png",
        "edition": "custom",
        "firstNight": 0,
        "firstNightReminder": "",
        "otherNight": 0,
        "otherNightReminder": "",
        "reminders": [
            "获得信息",
            "获得能力",
            "潘多拉的代价"
        ],
        "remindersGlobal": [
        ],
        "setup": false,
        "name": "古物商贩",
        "team": "traveler",
        "sch_team": "旅行者",
        "ability": "限一次，白天你可以打开魔盒获得一条重要信息或能力，但是会有人承担相对应的代价。"
    },
    {
        "id": "BeggarButton",
        "image": "https://oss.gstonegames.com/data_file/clocktower/web/icons/beggar.png",
        "edition": "custom",
        "firstNight": 0,
        "firstNightReminder": "",
        "otherNight": 0,
        "otherNightReminder": "",
        "reminders": [
        ],
        "remindersGlobal": [
        ],
        "setup": false,
        "name": "乞丐",
        "team": "traveler",
        "sch_team": "旅行者",
        "ability": "你只能使用投票标记才能投票。死亡的玩家可以将他的投票标记给你，如果他这么做，你会得知他的阵营。你不会中毒和醉酒。"
    },
    {
        "id": "MatronButton",
        "image": "https://oss.gstonegames.com/data_file/clocktower/web/icons/matron.png",
        "edition": "custom",
        "firstNight": 0,
        "firstNightReminder": "",
        "otherNight": 0,
        "otherNightReminder": "",
        "reminders": [
        ],
        "remindersGlobal": [
        ],
        "setup": false,
        "name": "女舍监",
        "team": "traveler",
        "sch_team": "旅行者",
        "ability": "每个白天，你可以选择至多三对玩家交换座位。玩家不能离开座位私聊。"
    },
    {
        "id": "VoudonButton",
        "image": "https://oss.gstonegames.com/data_file/clocktower/web/icons/voudon.png",
        "edition": "custom",
        "firstNight": 0,
        "firstNightReminder": "",
        "otherNight": 0,
        "otherNightReminder": "",
        "reminders": [
        ],
        "remindersGlobal": [
        ],
        "setup": false,
        "name": "巫毒师",
        "team": "traveler",
        "sch_team": "旅行者",
        "ability": "只有你和死亡的玩家可以投票，且投票不需要使用投票标记。忽略票数需要过半的要求。"
    },
    {
        "id": "ApprenticeButton",
        "image": "https://oss.gstonegames.com/data_file/clocktower/web/icons/apprentice.png",
        "edition": "custom",
        "firstNight": 1,
        "firstNightReminder": "向学徒展示“你是”信息标记，然后展示一个镇民或爪牙的角色标记。在魔典上，将学徒的角色标记替换为刚刚展示的角色标记，并放置“是学徒”提示标记。",
        "otherNight": 0,
        "otherNightReminder": "",
        "reminders": [
            "是学徒"
        ],
        "remindersGlobal": [
        ],
        "setup": false,
        "name": "学徒",
        "team": "traveler",
        "sch_team": "旅行者",
        "ability": "在你的首个夜晚，如果你是善良的，你会获得一个镇民角色的能力；如果你是邪恶的，你会获得一个爪牙角色的能力。"
    },
    {
        "id": "DeviantButton",
        "image": "https://oss.gstonegames.com/data_file/clocktower/web/icons/deviant.png",
        "edition": "custom",
        "firstNight": 0,
        "firstNightReminder": "",
        "otherNight": 0,
        "otherNightReminder": "",
        "reminders": [
        ],
        "remindersGlobal": [
        ],
        "setup": false,
        "name": "怪咖",
        "team": "traveler",
        "sch_team": "旅行者",
        "ability": "如果你表现得很有趣，当天你不能被流放。"
    },
    {
        "id": "Bone_CollectorButton",
        "image": "https://oss.gstonegames.com/data_file/clocktower/web/icons/bone_collector.png",
        "edition": "custom",
        "firstNight": 0,
        "firstNightReminder": "",
        "otherNight": 1,
        "otherNightReminder": "唤醒集骨者。集骨者要么摇头表示不使用能力，或者是指向任何一名已死亡的玩家。",
        "reminders": [
            "重获能力",
            "失去能力"
        ],
        "remindersGlobal": [
        ],
        "setup": false,
        "name": "集骨者",
        "team": "traveler",
        "sch_team": "旅行者",
        "ability": "每局游戏限一次，在夜晚时*，你可以选择一名死亡的玩家：他重新获得能力直到下个黄昏。"
    },
    {
        "id": "BaristaButton",
        "image": "https://oss.gstonegames.com/data_file/clocktower/web/icons/barista.png",
        "edition": "custom",
        "firstNight": 1,
        "firstNightReminder": "说书人选择一名玩家唤醒，并告诉他触发了咖啡师的什么效果。",
        "otherNight": 1,
        "otherNightReminder": "说书人选择一名玩家唤醒，并告诉他触发了咖啡师的什么效果。",
        "reminders": [
            "清醒且健康",
            "行动两次",
            "？"
        ],
        "remindersGlobal": [
        ],
        "setup": false,
        "name": "咖啡师",
        "team": "traveler",
        "sch_team": "旅行者",
        "ability": "每个夜晚，直至下个黄昏，由说书人二选一：1）一名玩家解除并免受醉酒和中毒影响，且会得知正确信息；2）一名玩家的能力可以生效两次。该玩家会得知是哪个效果。"
    },
    {
        "id": "HarlotButton",
        "image": "https://oss.gstonegames.com/data_file/clocktower/web/icons/harlot.png",
        "edition": "custom",
        "firstNight": 0,
        "firstNightReminder": "",
        "otherNight": 1,
        "otherNightReminder": "流莺选择一名玩家，将其唤醒，那名玩家选择同意或拒绝。如果同意，将他的角色标记展示给流莺看。然后说书人可以决定两名玩家是否会一起死去。",
        "reminders": [
            "死亡"
        ],
        "remindersGlobal": [
        ],
        "setup": false,
        "name": "流莺",
        "team": "traveler",
        "sch_team": "旅行者",
        "ability": "每个夜晚*，你要选择一名存活的玩家：如果他同意，你会得知他的角色，但是你们两个可能同时死亡。"
    },
    {
        "id": "GangsterButton",
        "image": "https://oss.gstonegames.com/data_file/clocktower/web/icons/gangster.png",
        "edition": "custom",
        "firstNight": 0,
        "firstNightReminder": "",
        "otherNight": 0,
        "otherNightReminder": "",
        "reminders": [
        ],
        "remindersGlobal": [
        ],
        "setup": false,
        "name": "黑帮",
        "team": "traveler",
        "sch_team": "旅行者",
        "ability": "每个白天限一次，你可以杀死与你邻近的两名存活的玩家中的一名，但需要另一边那个存活的玩家同意。"
    },
    {
        "id": "DoomsayerButton",
        "image": "https://oss.gstonegames.com/data_file/clocktower/web/icons/doomsayer.png",
        "edition": "custom",
        "firstNight": 0,
        "firstNightReminder": "",
        "otherNight": 0,
        "otherNightReminder": "",
        "reminders": [
        ],
        "remindersGlobal": [
        ],
        "setup": false,
        "name": "末日预言者",
        "team": "fabled",
        "sch_team": "传奇角色",
        "ability": "如果大于等于四名玩家存活，每名当前存活的玩家可以公开要求你杀死一名与他阵营相同的玩家（每名玩家限一次）。"
    },
    {
        "id": "AngelButton",
        "image": "https://oss.gstonegames.com/data_file/clocktower/web/icons/angel.png",
        "edition": "custom",
        "firstNight": 0,
        "firstNightReminder": "",
        "otherNight": 0,
        "otherNightReminder": "",
        "reminders": [
            "庇护",
            "不好的事"
        ],
        "remindersGlobal": [
        ],
        "setup": false,
        "name": "天使",
        "team": "fabled",
        "sch_team": "传奇角色",
        "ability": "对新玩家的死亡负最大责任的人，可能会遭遇一些不好的事情。"
    },
    {
        "id": "BuddhistButton",
        "image": "https://oss.gstonegames.com/data_file/clocktower/web/icons/buddhist.png",
        "edition": "custom",
        "firstNight": 0,
        "firstNightReminder": "",
        "otherNight": 0,
        "otherNightReminder": "",
        "reminders": [
        ],
        "remindersGlobal": [
        ],
        "setup": false,
        "name": "佛教徒",
        "team": "fabled",
        "sch_team": "传奇角色",
        "ability": "每个白天的前两分钟老玩家不能发言。"
    },
    {
        "id": "Hells_LibrarianButton",
        "image": "https://oss.gstonegames.com/data_file/clocktower/web/icons/hells_librarian.png",
        "edition": "custom",
        "firstNight": 0,
        "firstNightReminder": "",
        "otherNight": 0,
        "otherNightReminder": "",
        "reminders": [
            "不好的事"
        ],
        "remindersGlobal": [
        ],
        "setup": false,
        "name": "地狱藏书员",
        "team": "fabled",
        "sch_team": "传奇角色",
        "ability": "当说书人宣布安静时，仍在说话的玩家可能会遭遇一些不好的事情。"
    },
    {
        "id": "FiddlerButton",
        "image": "https://oss.gstonegames.com/data_file/clocktower/web/icons/fiddler.png",
        "edition": "custom",
        "firstNight": 0,
        "firstNightReminder": "",
        "otherNight": 0,
        "otherNightReminder": "",
        "reminders": [
        ],
        "remindersGlobal": [
        ],
        "setup": false,
        "name": "小提琴手",
        "team": "fabled",
        "sch_team": "传奇角色",
        "ability": "每局游戏限一次，恶魔可以秘密选择一名对立阵营的玩家，所有玩家要表决：这两名玩家中谁的阵营获胜。（平局邪恶阵营获胜）"
    },
    {
        "id": "DuchessButton",
        "image": "https://oss.gstonegames.com/data_file/clocktower/web/icons/duchess.png",
        "edition": "custom",
        "firstNight": 0,
        "firstNightReminder": "",
        "otherNight": 0,
        "otherNightReminder": "",
        "reminders": [
            "访客",
            "错误信息"
        ],
        "remindersGlobal": [
        ],
        "setup": false,
        "name": "公爵夫人",
        "team": "fabled",
        "sch_team": "传奇角色",
        "ability": "每个白天，三名玩家可以一起拜访你。当晚*，他们会得知他们之中有几个是邪恶的，但其中一人的信息是错的。"
    },
    {
        "id": "Spirit_Of_IvoryButton",
        "image": "https://oss.gstonegames.com/data_file/clocktower/web/icons/spirit_of_ivory.png",
        "edition": "custom",
        "firstNight": 0,
        "firstNightReminder": "",
        "otherNight": 0,
        "otherNightReminder": "",
        "reminders": [
            "禁止邪恶"
        ],
        "remindersGlobal": [
        ],
        "setup": false,
        "name": "圣洁之魂",
        "team": "fabled",
        "sch_team": "传奇角色",
        "ability": "游戏过程中邪恶玩家的总数最多能比初始设置多一名。"
    },
    {
        "id": "DjinnButton",
        "image": "https://oss.gstonegames.com/data_file/clocktower/web/icons/djinn.png",
        "edition": "custom",
        "firstNight": 0,
        "firstNightReminder": "",
        "otherNight": 0,
        "otherNightReminder": "",
        "reminders": [
        ],
        "remindersGlobal": [
        ],
        "setup": false,
        "name": "灯神",
        "team": "fabled",
        "sch_team": "传奇角色",
        "ability": "使用灯神的相克规则。所有玩家都会知道其内容。"
    },
    {
        "id": "BootleggerButton",
        "image": "https://oss.gstonegames.com/data_file/clocktower/web/icons/bootlegger.png",
        "edition": "custom",
        "firstNight": 0,
        "firstNightReminder": "",
        "otherNight": 0,
        "otherNightReminder": "",
        "reminders": [
        ],
        "remindersGlobal": [
        ],
        "setup": false,
        "name": "私货商人",
        "team": "fabled",
        "sch_team": "传奇角色",
        "ability": "这个剧本包含有自制角色或自制规则。"
    },
    {
        "id": "Bootlegger_AmnesiacButton",
        "image": "https://oss.gstonegames.com/data_file/clocktower/web/icons/bootlegger.png",
        "edition": "custom",
        "firstNight": 0,
        "firstNightReminder": "",
        "otherNight": 0,
        "otherNightReminder": "",
        "reminders": [
        ],
        "remindersGlobal": [
        ],
        "setup": false,
        "name": "私货商人",
        "team": "fabled",
        "sch_team": "传奇角色",
        "ability": "本局失忆者共有两段能力。能力一来自钟楼百科可查询到的角色能力。能力二来自热门自制剧本角色能力。每个白天，失忆者可分别猜测能力一/二，并得知无关/有关/接近/完美。失忆者无设置调整能力。"
    },
    {
        "id": "FerrymanButton",
        "image": "https://wiki.bloodontheclocktower.com/images/8/8f/Icon_ferryman.png",
        "edition": "custom",
        "firstNight": 0,
        "firstNightReminder": "",
        "otherNight": 0,
        "otherNightReminder": "",
        "reminders": [
        ],
        "remindersGlobal": [
        ],
        "setup": false,
        "name": "摆渡人",
        "team": "fabled",
        "sch_team": "传奇角色",
        "ability": "在游戏的最后一天，所有已死亡玩家会重新获得投票标记。"
    },
    {
        "id": "GardenerButton",
        "image": "https://oss.gstonegames.com/data_file/clocktower/web/icons/gardener.png",
        "edition": "custom",
        "firstNight": 0,
        "firstNightReminder": "",
        "otherNight": 0,
        "otherNightReminder": "",
        "reminders": [
        ],
        "remindersGlobal": [
        ],
        "setup": false,
        "name": "园丁",
        "team": "fabled",
        "sch_team": "传奇角色",
        "ability": "由说书人来为一名或更多玩家派发角色。"
    },
    {
        "id": "Storm_CatcherButton",
        "image": "https://oss.gstonegames.com/data_file/clocktower/web/icons/stormcatcher.png",
        "edition": "custom",
        "firstNight": 1,
        "firstNightReminder": "标记一个善良玩家安全，或者不标。依次唤醒所有邪恶玩家并告知谁是安全的，或者不唤醒。",
        "otherNight": 0,
        "otherNightReminder": "",
        "reminders": [
        ],
        "remindersGlobal": [
        ],
        "setup": false,
        "name": "暴风捕手",
        "team": "fabled",
        "sch_team": "传奇角色",
        "ability": "游戏开始时，你要宣布一个善良角色。如果该角色在场，他只能死于处决，但所有邪恶玩家会在首个夜晚得知他是哪一名玩家。"
    }
]